nexuslabdata/exceptions.py
nexuslabdata/py.typed
nexuslabdata/cli/cli_events.py
nexuslabdata/cli/cli_exceptions.py
nexuslabdata/cli/cli_utils.py
nexuslabdata/cli/cli_variables.py
nexuslabdata/cli/main.py
nexuslabdata/cli/params.py
nexuslabdata/cli/requires.py
nexuslabdata/cli/requires_wrapper.py
nexuslabdata/cli/connection/main_connection.py
nexuslabdata/cli/connection/requires_connection.py
nexuslabdata/cli/context/__init__.py
nexuslabdata/cli/context/context.py
nexuslabdata/cli/flow/main_flow.py
nexuslabdata/cli/flow/task_data_flow_exec.py
nexuslabdata/cli/project/main_project.py
nexuslabdata/cli/structure/main_structure.py
nexuslabdata/config/data_product.py
nexuslabdata/connection/base/__init__.py
nexuslabdata/connection/base/connection.py
nexuslabdata/connection/base/connection_info.py
nexuslabdata/connection/base/credential.py
nexuslabdata/connection/base/default_connection_info.py
nexuslabdata/connection/base/events.py
nexuslabdata/connection/base/exceptions.py
nexuslabdata/connection/base/plugin.py
nexuslabdata/connection/base/query.py
nexuslabdata/connection/base/service.py
nexuslabdata/connection/manager/__init__.py
nexuslabdata/connection/manager/events.py
nexuslabdata/connection/manager/factory.py
nexuslabdata/connection/manager/manager.py
nexuslabdata/connection/task/__init__.py
nexuslabdata/connection/task/connection_debug.py
nexuslabdata/core/__init__.py
nexuslabdata/core/events.py
nexuslabdata/core/exceptions.py
nexuslabdata/core/field/__init__.py
nexuslabdata/core/field/field.py
nexuslabdata/core/field/field_adapter.py
nexuslabdata/core/field/field_characterisation.py
nexuslabdata/core/field/field_characterisation_def.py
nexuslabdata/core/field/field_data_type.py
nexuslabdata/core/field/field_flatten_adapter.py
nexuslabdata/core/field/field_format_adapter.py
nexuslabdata/core/field/field_template.py
nexuslabdata/core/flow/__init__.py
nexuslabdata/core/flow/events.py
nexuslabdata/core/flow/exceptions.py
nexuslabdata/core/flow/base/__init__.py
nexuslab_data_core-0.0.1a1.dist-info/METADATA
nexuslab_data_core-0.0.1a1.dist-info/WHEEL
nexuslab_data_core-0.0.1a1.dist-info/entry_points.txt
nexuslab_data_core-0.0.1a1.dist-info/top_level.txt
nexuslab_data_core-0.0.1a1.dist-info/RECORD
